Workbook

Sheet Dashboard
B2: EXPENSE TRACKER | FINANCIAL COMMAND CENTER
B3: Real-time insights into your income, spending, savings, and budget performance
B5: TOTAL INCOME | D5: TOTAL EXPENSES | G5: NET SAVINGS | J5: SAVINGS RATE
B6: =SUMIF(Transactions!E:E,"Income",Transactions!F:F) -> 7335.5 | D6: =SUMIF(Transactions!E:E,"Expense",Transactions!F:F) -> 3647 | G6: =B6-D6 -> 3688.5 | J6: =IFERROR(G6/B6,0) -> 0.50282871
B7: ▲ All Income Sources | D7: ▼ All Categories | G7: ● Income − Expenses | J7: % of Income Saved
B11: BUDGET UTILIZATION | D11: AVG DAILY SPEND | G11: TOP SPEND CATEGORY | J11: TRANSACTIONS
B12: =IFERROR(D6/SUM(Budget!C5:C14),0) -> 0.73975659 | D12: =IFERROR(D6/30,0) -> 121.56667 | G12: {=INDEX(Categories!B5:B14,MATCH(MAX(Categories!D5:D14),Categories!D5:D14,0))} -> Savings Goal | J12: =COUNTA(Transactions!B5:B500) -> 31
B13: Of Total Monthly Budget | D13: Based on 30 Days | G13: =" $ "&TEXT(MAX(Categories!D5:D14),"#,##0")&" Spent" -> $ 3,689 Spent | J13: Total Logged Entries
B17: SPENDING BY CATEGORY | G17: MONTHLY TREND
B19: Category | C19: Budget | D19: Actual | E19: % Used | G19: Month | H19: Income | I19: Expenses | J19: Savings | K19: Save %
B20: =Categories!B5 -> Housing | C20: =Categories!C5 -> 1700 | D20: =Categories!D5 -> 1665.4 | E20: =IFERROR(Categories!D5/Categories!C5,0) -> 0.97964706 | G20: =Monthly!B5 -> Jul 2025 | H20: =Monthly!C5 -> 5800 | I20: =Monthly!D5 -> 4200 | J20: =Monthly!C5-Monthly!D5 -> 1600 | K20: =IFERROR((Monthly!C5-Monthly!D5)/Monthly!C5,0) -> 0.27586207
B21: =Categories!B6 -> Food & Dining | C21: =Categories!C6 -> 600 | D21: =Categories!D6 -> 419.4 | E21: =IFERROR(Categories!D6/Categories!C6,0) -> 0.699 | G21: =Monthly!B6 -> Aug 2025 | H21: =Monthly!C6 -> 5800 | I21: =Monthly!D6 -> 4450 | J21: =Monthly!C6-Monthly!D6 -> 1350 | K21: =IFERROR((Monthly!C6-Monthly!D6)/Monthly!C6,0) -> 0.23275862
B22: =Categories!B7 -> Transportation | C22: =Categories!C7 -> 400 | D22: =Categories!D7 -> 268.05 | E22: =IFERROR(Categories!D7/Categories!C7,0) -> 0.670125 | G22: =Monthly!B7 -> Sep 2025 | H22: =Monthly!C7 -> 6100 | I22: =Monthly!D7 -> 4380 | J22: =Monthly!C7-Monthly!D7 -> 1720 | K22: =IFERROR((Monthly!C7-Monthly!D7)/Monthly!C7,0) -> 0.28196721
B23: =Categories!B8 -> Utilities | C23: =Categories!C8 -> 280 | D23: =Categories!D8 -> 240.39 | E23: =IFERROR(Categories!D8/Categories!C8,0) -> 0.85853571 | G23: =Monthly!B8 -> Oct 2025 | H23: =Monthly!C8 -> 5800 | I23: =Monthly!D8 -> 4720 | J23: =Monthly!C8-Monthly!D8 -> 1080 | K23: =IFERROR((Monthly!C8-Monthly!D8)/Monthly!C8,0) -> 0.1862069
B24: =Categories!B9 -> Entertainment | C24: =Categories!C9 -> 250 | D24: =Categories!D9 -> 251.48 | E24: =IFERROR(Categories!D9/Categories!C9,0) -> 1.00592 | G24: =Monthly!B9 -> Nov 2025 | H24: =Monthly!C9 -> 6300 | I24: =Monthly!D9 -> 4890 | J24: =Monthly!C9-Monthly!D9 -> 1410 | K24: =IFERROR((Monthly!C9-Monthly!D9)/Monthly!C9,0) -> 0.22380952
B25: =Categories!B10 -> Shopping | C25: =Categories!C10 -> 350 | D25: =Categories!D10 -> 281.79 | E25: =IFERROR(Categories!D10/Categories!C10,0) -> 0.80511429 | G25: =Monthly!B10 -> Dec 2025 | H25: =Monthly!C10 -> 6800 | I25: =Monthly!D10 -> 5410 | J25: =Monthly!C10-Monthly!D10 -> 1390 | K25: =IFERROR((Monthly!C10-Monthly!D10)/Monthly!C10,0) -> 0.20441176
B26: =Categories!B11 -> Healthcare | C26: =Categories!C11 -> 200 | D26: =Categories!D11 -> 202.5 | E26: =IFERROR(Categories!D11/Categories!C11,0) -> 1.0125 | G26: =Monthly!B11 -> Jan 2026 | H26: =Monthly!C11 -> 5900 | I26: =Monthly!D11 -> 4350 | J26: =Monthly!C11-Monthly!D11 -> 1550 | K26: =IFERROR((Monthly!C11-Monthly!D11)/Monthly!C11,0) -> 0.26271186
B27: =Categories!B12 -> Education | C27: =Categories!C12 -> 150 | D27: =Categories!D12 -> 137.99 | E27: =IFERROR(Categories!D12/Categories!C12,0) -> 0.91993333 | G27: =Monthly!B12 -> Feb 2026 | H27: =Monthly!C12 -> 6050 | I27: =Monthly!D12 -> 4180 | J27: =Monthly!C12-Monthly!D12 -> 1870 | K27: =IFERROR((Monthly!C12-Monthly!D12)/Monthly!C12,0) -> 0.30909091
B28: =Categories!B13 -> Miscellaneous | C28: =Categories!C13 -> 200 | D28: =Categories!D13 -> 180 | E28: =IFERROR(Categories!D13/Categories!C13,0) -> 0.9 | G28: =Monthly!B13 -> Mar 2026 | H28: =Monthly!C13 -> 6200 | I28: =Monthly!D13 -> 4520 | J28: =Monthly!C13-Monthly!D13 -> 1680 | K28: =IFERROR((Monthly!C13-Monthly!D13)/Monthly!C13,0) -> 0.27096774
B29: =Categories!B14 -> Savings Goal | C29: =Categories!C14 -> 800 | D29: =Categories!D14 -> 3688.5 | E29: =IFERROR(Categories!D14/Categories!C14,0) -> 4.610625 | G29: =Monthly!B14 -> Apr 2026 | H29: =Monthly!C14 -> 7335 | I29: =Monthly!D14 -> 4150 | J29: =Monthly!C14-Monthly!D14 -> 3185 | K29: =IFERROR((Monthly!C14-Monthly!D14)/Monthly!C14,0) -> 0.4342195
B30: TOTAL | C30: =SUM(C20:C29) -> 4930 | D30: =SUM(D20:D29) -> 7335.5 | E30: =IFERROR(D30/C30,0) -> 1.487931 | G30: TOTAL | H30: =SUM(H20:H29) -> 62085 | I30: =SUM(I20:I29) -> 45250 | J30: =H30-I30 -> 16835 | K30: =IFERROR(J30/H30,0) -> 0.27116051
B33: KEY INSIGHTS & RECOMMENDATIONS
B35: FINANCIAL HEALTH | E35: BUDGET STATUS | H35: ACTION ITEM
B36: =IF(J6>0.2,"EXCELLENT - You're saving over 20% of income, building wealth efficiently.",IF(J6>0.1,"GOOD - Solid savings rate. Consider increasing to 20%+ for stronger growth.",IF(J6>0,"FAIR - Positive but tight. Review discretionary spending.","ALERT - Spending exceeds income. Immediate budget review needed."))) -> EXCELLENT - You're saving over 20% of income, building wealth efficiently. | E36: =IF(B12<0.8,"ON TRACK - Spending well within budget limits.",IF(B12<1,"CAUTION - Approaching budget ceiling. Monitor closely.","OVER BUDGET - Exceeded planned limits. Adjust required.")) -> ON TRACK - Spending well within budget limits. | H36: {="Focus on "&INDEX(Categories!B5:B14,MATCH(MAX(Categories!D5:D14),Categories!D5:D14,0))&" - your highest spending category at $"&TEXT(MAX(Categories!D5:D14),"#,##0")&"."} -> Focus on Savings Goal - your highest spending category at $3,689.
B38: Powered by Smart Finance • Update transactions on the Transactions tab to refresh dashboard automatically

Sheet Transactions
B2: TRANSACTION LEDGER
B3: Add new transactions below — categories pull from Categories tab
B4: Date | C4: Description | D4: Category | E4: Type | F4: Amount | G4: Payment Method | H4: Notes
B5: 2026-04-01 | C5: Monthly Salary | D5: Salary | E5: Income | F5: 5500 | G5: Direct Deposit | H5: Primary employment
B6: 2026-04-01 | C6: Rent Payment | D6: Housing | E6: Expense | F6: 1450 | G6: Bank Transfer | H6: Monthly apartment rent
B7: 2026-04-02 | C7: Grocery - Whole Foods | D7: Food & Dining | E7: Expense | F7: 142.5 | G7: Credit Card | H7: Weekly groceries
B8: 2026-04-03 | C8: Gas Station Fill-up | D8: Transportation | E8: Expense | F8: 58.75 | G8: Credit Card
B9: 2026-04-04 | C9: Netflix Subscription | D9: Entertainment | E9: Expense | F9: 15.99 | G9: Credit Card | H9: Monthly subscription
B10: 2026-04-05 | C10: Electricity Bill | D10: Utilities | E10: Expense | F10: 95.4 | G10: Bank Transfer | H10: April utilities
B11: 2026-04-06 | C11: Restaurant - Italian | D11: Food & Dining | E11: Expense | F11: 78.25 | G11: Credit Card | H11: Anniversary dinner
B12: 2026-04-07 | C12: Internet Bill | D12: Utilities | E12: Expense | F12: 79.99 | G12: Auto-Pay | H12: Monthly internet
B13: 2026-04-08 | C13: Freelance Project | D13: Side Income | E13: Income | F13: 850 | G13: PayPal | H13: Logo design work
B14: 2026-04-09 | C14: Pharmacy | D14: Healthcare | E14: Expense | F14: 32.5 | G14: Debit Card | H14: Prescription
B15: 2026-04-10 | C15: Coffee Shop | D15: Food & Dining | E15: Expense | F15: 18.75 | G15: Credit Card | H15: Weekly coffees
B16: 2026-04-11 | C16: Amazon Purchase | D16: Shopping | E16: Expense | F16: 124.99 | G16: Credit Card | H16: Office supplies
B17: 2026-04-12 | C17: Gym Membership | D17: Healthcare | E17: Expense | F17: 45 | G17: Auto-Pay | H17: Monthly fitness
B18: 2026-04-13 | C18: Uber Rides | D18: Transportation | E18: Expense | F18: 67.3 | G18: Credit Card | H18: Weekly transportation
B19: 2026-04-14 | C19: Phone Bill | D19: Utilities | E19: Expense | F19: 65 | G19: Auto-Pay | H19: Cellular service
B20: 2026-04-15 | C20: Investment Dividend | D20: Investments | E20: Income | F20: 235.5 | G20: Bank Transfer | H20: Quarterly dividend
... B34: 2026-04-29 | C34: Charity Donation | D34: Miscellaneous | E34: Expense | F34: 100 | G34: Bank Transfer | H34: Local foundation
B36: SUMMARY | E36: NET | F36: =SUMIF(E5:E34,"Income",F5:F34)-SUMIF(E5:E34,"Expense",F5:F34) -> 3688.5 | G36: Income − Expenses

Sheet Categories
B2: CATEGORY ANALYSIS & BUDGET TRACKING
B3: Monthly budget allocations and live spending performance by category
B4: Category | C4: Monthly Budget | D4: Actual Spent | E4: Remaining | F4: % Used | G4: Status | H4: Trend Note
B5: Housing | C5: 1700 | D5: =SUMIFS(Transactions!F:F,Transactions!D:D,B5,Transactions!E:E,"Expense") -> 1665.4 | E5: =C5-D5 -> 34.6 | F5: =IFERROR(D5/C5,0) -> 0.97964706 | G5: =IF(F5>1,"⚠ OVER",IF(F5>0.85,"⚡ NEAR LIMIT",IF(F5>0.5,"✓ ON TRACK","◯ UNDER"))) -> ⚡ NEAR LIMIT | H5: Rent, mortgage, repairs
B6: Food & Dining | C6: 600 | D6: =SUMIFS(Transactions!F:F,Transactions!D:D,B6,Transactions!E:E,"Expense") -> 419.4 | E6: =C6-D6 -> 180.6 | F6: =IFERROR(D6/C6,0) -> 0.699 | G6: =IF(F6>1,"⚠ OVER",IF(F6>0.85,"⚡ NEAR LIMIT",IF(F6>0.5,"✓ ON TRACK","◯ UNDER"))) -> ✓ ON TRACK | H6: Groceries and restaurants
B7: Transportation | C7: 400 | D7: =SUMIFS(Transactions!F:F,Transactions!D:D,B7,Transactions!E:E,"Expense") -> 268.05 | E7: =C7-D7 -> 131.95 | F7: =IFERROR(D7/C7,0) -> 0.670125 | G7: =IF(F7>1,"⚠ OVER",IF(F7>0.85,"⚡ NEAR LIMIT",IF(F7>0.5,"✓ ON TRACK","◯ UNDER"))) -> ✓ ON TRACK | H7: Gas, insurance, rideshare
B8: Utilities | C8: 280 | D8: =SUMIFS(Transactions!F:F,Transactions!D:D,B8,Transactions!E:E,"Expense") -> 240.39 | E8: =C8-D8 -> 39.61 | F8: =IFERROR(D8/C8,0) -> 0.85853571 | G8: =IF(F8>1,"⚠ OVER",IF(F8>0.85,"⚡ NEAR LIMIT",IF(F8>0.5,"✓ ON TRACK","◯ UNDER"))) -> ⚡ NEAR LIMIT | H8: Electric, internet, phone
B9: Entertainment | C9: 250 | D9: =SUMIFS(Transactions!F:F,Transactions!D:D,B9,Transactions!E:E,"Expense") -> 251.48 | E9: =C9-D9 -> -1.48 | F9: =IFERROR(D9/C9,0) -> 1.00592 | G9: =IF(F9>1,"⚠ OVER",IF(F9>0.85,"⚡ NEAR LIMIT",IF(F9>0.5,"✓ ON TRACK","◯ UNDER"))) -> ⚠ OVER | H9: Streaming, events, hobbies
B10: Shopping | C10: 350 | D10: =SUMIFS(Transactions!F:F,Transactions!D:D,B10,Transactions!E:E,"Expense") -> 281.79 | E10: =C10-D10 -> 68.21 | F10: =IFERROR(D10/C10,0) -> 0.80511429 | G10: =IF(F10>1,"⚠ OVER",IF(F10>0.85,"⚡ NEAR LIMIT",IF(F10>0.5,"✓ ON TRACK","◯ UNDER"))) -> ✓ ON TRACK | H10: Clothing and personal items
B11: Healthcare | C11: 200 | D11: =SUMIFS(Transactions!F:F,Transactions!D:D,B11,Transactions!E:E,"Expense") -> 202.5 | E11: =C11-D11 -> -2.5 | F11: =IFERROR(D11/C11,0) -> 1.0125 | G11: =IF(F11>1,"⚠ OVER",IF(F11>0.85,"⚡ NEAR LIMIT",IF(F11>0.5,"✓ ON TRACK","◯ UNDER"))) -> ⚠ OVER | H11: Insurance, gym, prescriptions
B12: Education | C12: 150 | D12: =SUMIFS(Transactions!F:F,Transactions!D:D,B12,Transactions!E:E,"Expense") -> 137.99 | E12: =C12-D12 -> 12.01 | F12: =IFERROR(D12/C12,0) -> 0.91993333 | G12: =IF(F12>1,"⚠ OVER",IF(F12>0.85,"⚡ NEAR LIMIT",IF(F12>0.5,"✓ ON TRACK","◯ UNDER"))) -> ⚡ NEAR LIMIT | H12: Courses, books, training
B13: Miscellaneous | C13: 200 | D13: =SUMIFS(Transactions!F:F,Transactions!D:D,B13,Transactions!E:E,"Expense") -> 180 | E13: =C13-D13 -> 20 | F13: =IFERROR(D13/C13,0) -> 0.9 | G13: =IF(F13>1,"⚠ OVER",IF(F13>0.85,"⚡ NEAR LIMIT",IF(F13>0.5,"✓ ON TRACK","◯ UNDER"))) -> ⚡ NEAR LIMIT | H13: Cash, donations, other
B14: Savings Goal | C14: 800 | D14: =MAX(0,Dashboard!G6) -> 3688.5 | E14: =C14-D14 -> -2888.5 | F14: =IFERROR(D14/C14,0) -> 4.610625 | G14: =IF(F14>1,"⚠ OVER",IF(F14>0.85,"⚡ NEAR LIMIT",IF(F14>0.5,"✓ ON TRACK","◯ UNDER"))) -> ⚠ OVER | H14: Target monthly savings
B15: TOTAL | C15: =SUM(C5:C14) -> 4930 | D15: =SUM(D5:D14) -> 7335.5 | E15: =C15-D15 -> -2405.5 | F15: =IFERROR(D15/C15,0) -> 1.487931 | G15: OVERALL BUDGET PERFORMANCE

Sheet Budget
B2: BUDGET PLAN & ALLOCATION STRATEGY
B3: Plan annual budget by category — auto-syncs to Categories analysis
B4: Category | C4: Monthly Budget | D4: Quarterly | E4: Annual | F4: % of Income | G4: 50/30/20 Rule
B5: =Categories!B5 -> Housing | C5: =Categories!C5 -> 1700 | D5: =C5*3 -> 5100 | E5: =C5*12 -> 20400 | F5: =IFERROR(C5/Dashboard!B6,0) -> 0.23174971 | G5: Needs (50%)
B6: =Categories!B6 -> Food & Dining | C6: =Categories!C6 -> 600 | D6: =C6*3 -> 1800 | E6: =C6*12 -> 7200 | F6: =IFERROR(C6/Dashboard!B6,0) -> 0.081794015 | G6: Needs (50%)
B7: =Categories!B7 -> Transportation | C7: =Categories!C7 -> 400 | D7: =C7*3 -> 1200 | E7: =C7*12 -> 4800 | F7: =IFERROR(C7/Dashboard!B6,0) -> 0.054529344 | G7: Needs (50%)
B8: =Categories!B8 -> Utilities | C8: =Categories!C8 -> 280 | D8: =C8*3 -> 840 | E8: =C8*12 -> 3360 | F8: =IFERROR(C8/Dashboard!B6,0) -> 0.038170541 | G8: Needs (50%)
B9: =Categories!B9 -> Entertainment | C9: =Categories!C9 -> 250 | D9: =C9*3 -> 750 | E9: =C9*12 -> 3000 | F9: =IFERROR(C9/Dashboard!B6,0) -> 0.03408084 | G9: Needs (50%)
B10: =Categories!B10 -> Shopping | C10: =Categories!C10 -> 350 | D10: =C10*3 -> 1050 | E10: =C10*12 -> 4200 | F10: =IFERROR(C10/Dashboard!B6,0) -> 0.047713176 | G10: Wants (30%)
B11: =Categories!B11 -> Healthcare | C11: =Categories!C11 -> 200 | D11: =C11*3 -> 600 | E11: =C11*12 -> 2400 | F11: =IFERROR(C11/Dashboard!B6,0) -> 0.027264672 | G11: Wants (30%)
B12: =Categories!B12 -> Education | C12: =Categories!C12 -> 150 | D12: =C12*3 -> 450 | E12: =C12*12 -> 1800 | F12: =IFERROR(C12/Dashboard!B6,0) -> 0.020448504 | G12: Wants (30%)
B13: =Categories!B13 -> Miscellaneous | C13: =Categories!C13 -> 200 | D13: =C13*3 -> 600 | E13: =C13*12 -> 2400 | F13: =IFERROR(C13/Dashboard!B6,0) -> 0.027264672 | G13: Wants (30%)
B14: =Categories!B14 -> Savings Goal | C14: =Categories!C14 -> 800 | D14: =C14*3 -> 2400 | E14: =C14*12 -> 9600 | F14: =IFERROR(C14/Dashboard!B6,0) -> 0.10905869 | G14: Savings (20%)
B15: TOTAL BUDGET | C15: =SUM(C5:C14) -> 4930 | D15: =SUM(D5:D14) -> 14790 | E15: =SUM(E5:E14) -> 59160 | F15: =SUM(F5:F14) -> 0.67207416 | G15: 100%
B18: 50/30/20 RULE COMPLIANCE
B19: Category | C19: Recommended | D19: Your Plan | E19: Difference | F19: Status
B20: Needs | C20: 0.5 | D20: =IFERROR(SUMIF(G5:G14,"Needs (50%)",C5:C14)/C15,0) -> 0.65517241 | E20: =D20-C20 -> 0.15517241 | F20: =IF(ABS(E20)<0.05,"✓ ALIGNED",IF(E20>0,"↑ HIGHER","↓ LOWER")) -> ↑ HIGHER | G20: Essential expenses
B21: Wants | C21: 0.3 | D21: =IFERROR(SUMIF(G5:G14,"Wants (30%)",C5:C14)/C15,0) -> 0.18255578 | E21: =D21-C21 -> -0.11744422 | F21: =IF(ABS(E21)<0.05,"✓ ALIGNED",IF(E21>0,"↑ HIGHER","↓ LOWER")) -> ↓ LOWER | G21: Lifestyle & discretionary
B22: Savings | C22: 0.2 | D22: =IFERROR(SUMIF(G5:G14,"Savings (20%)",C5:C14)/C15,0) -> 0.16227181 | E22: =D22-C22 -> -0.037728195 | F22: =IF(ABS(E22)<0.05,"✓ ALIGNED",IF(E22>0,"↑ HIGHER","↓ LOWER")) -> ✓ ALIGNED | G22: Future security

Sheet Monthly
B2: MONTHLY PERFORMANCE & TREND ANALYSIS
B3: 10-month rolling view of income, expenses, and savings performance
B4: Month | C4: Income | D4: Expenses | E4: Savings | F4: Save Rate | G4: Cumulative Savings | H4: Net Worth
B5: Jul 2025 | C5: 5800 | D5: 4200 | E5: =C5-D5 -> 1600 | F5: =IFERROR(E5/C5,0) -> 0.27586207 | G5: =E5 -> 1600 | H5: =12500+E5 -> 14100
B6: Aug 2025 | C6: 5800 | D6: 4450 | E6: =C6-D6 -> 1350 | F6: =IFERROR(E6/C6,0) -> 0.23275862 | G6: =G5+E6 -> 2950 | H6: =H5+E6 -> 15450
B7: Sep 2025 | C7: 6100 | D7: 4380 | E7: =C7-D7 -> 1720 | F7: =IFERROR(E7/C7,0) -> 0.28196721 | G7: =G6+E7 -> 4670 | H7: =H6+E7 -> 17170
B8: Oct 2025 | C8: 5800 | D8: 4720 | E8: =C8-D8 -> 1080 | F8: =IFERROR(E8/C8,0) -> 0.1862069 | G8: =G7+E8 -> 5750 | H8: =H7+E8 -> 18250
B9: Nov 2025 | C9: 6300 | D9: 4890 | E9: =C9-D9 -> 1410 | F9: =IFERROR(E9/C9,0) -> 0.22380952 | G9: =G8+E9 -> 7160 | H9: =H8+E9 -> 19660
B10: Dec 2025 | C10: 6800 | D10: 5410 | E10: =C10-D10 -> 1390 | F10: =IFERROR(E10/C10,0) -> 0.20441176 | G10: =G9+E10 -> 8550 | H10: =H9+E10 -> 21050
B11: Jan 2026 | C11: 5900 | D11: 4350 | E11: =C11-D11 -> 1550 | F11: =IFERROR(E11/C11,0) -> 0.26271186 | G11: =G10+E11 -> 10100 | H11: =H10+E11 -> 22600
B12: Feb 2026 | C12: 6050 | D12: 4180 | E12: =C12-D12 -> 1870 | F12: =IFERROR(E12/C12,0) -> 0.30909091 | G12: =G11+E12 -> 11970 | H12: =H11+E12 -> 24470
B13: Mar 2026 | C13: 6200 | D13: 4520 | E13: =C13-D13 -> 1680 | F13: =IFERROR(E13/C13,0) -> 0.27096774 | G13: =G12+E13 -> 13650 | H13: =H12+E13 -> 26150
B14: Apr 2026 | C14: 7335 | D14: 4150 | E14: =C14-D14 -> 3185 | F14: =IFERROR(E14/C14,0) -> 0.4342195 | G14: =G13+E14 -> 16835 | H14: =H13+E14 -> 29335
B15: 10-MO TOTAL | C15: =SUM(C5:C14) -> 62085 | D15: =SUM(D5:D14) -> 45250 | E15: =SUM(E5:E14) -> 16835 | F15: =IFERROR(E15/C15,0) -> 0.27116051 | G15: =G14 -> 16835 | H15: =H14 -> 29335
